punto_switcher/__init__.py
punto_switcher/__main__.py
punto_switcher/init.py
punto_switcher/keyboard_tracker.py
punto_switcher/main.py
punto_switcher/assets/icon.png
punto_switcher/assets/punto-switcher.desktop
punto_switcher/assets/sound.wav
punto_switcher-1.0.1.data/data/share/applications/punto-switcher.desktop
punto_switcher-1.0.1.data/data/share/icons/hicolor/48x48/apps/icon.png
punto_switcher-1.0.1.dist-info/licenses/LICENSE
punto_switcher-1.0.1.dist-info/METADATA
punto_switcher-1.0.1.dist-info/WHEEL
punto_switcher-1.0.1.dist-info/entry_points.txt
punto_switcher-1.0.1.dist-info/top_level.txt
punto_switcher-1.0.1.dist-info/RECORD
