Metadata-Version: 2.4
Name: punto_switcher
Version: 1.0.1
Summary: Keyboard layout autocorrector for Linux/X11
Author: Your Name
Author-email: your.email@example.com
License: MIT
Keywords: keyboard layout switcher autocorrect linux
Classifier: Development Status :: 5 - Production/Stable
Classifier: Environment :: Console
Classifier: Intended Audience :: End Users/Desktop
Classifier: License :: OSI Approved :: MIT License
Classifier: Operating System :: POSIX :: Linux
Classifier: Programming Language :: Python :: 3
Classifier: Topic :: Utilities
License-File: LICENSE
Requires-Dist: pyperclip>=1.8.0
Requires-Dist: pynput>=1.7.0
Requires-Dist: pyenchant>=3.2.0
Requires-Dist: pygame>=2.0.0
Dynamic: author
Dynamic: author-email
Dynamic: classifier
Dynamic: keywords
Dynamic: license
Dynamic: license-file
Dynamic: requires-dist
Dynamic: summary
